Cdatatype/__init__.py
datatype/__init__.py
tess/__init__.py
Cdatatype-1.0.1.dist-info/LICENSE
Cdatatype-1.0.1.dist-info/METADATA
Cdatatype-1.0.1.dist-info/WHEEL
Cdatatype-1.0.1.dist-info/top_level.txt
Cdatatype-1.0.1.dist-info/RECORD
