Metadata-Version: 2.1
Name: Cdatatype
Version: 1.0.1
Summary: A python package to count datatypes and null values in columns
Home-page: UNKNOWN
Author: Thiru Siddharth
Author-email: thirusid789@gmail.com
License: MIT
Platform: UNKNOWN
Classifier: License :: OSI Approved :: MIT License
Classifier: Programming Language :: Python :: 3
Classifier: Programming Language :: Python :: 3.8
Requires-Dist: pandas
